MANIFEST.in
README.md
requirements.in
requirements.txt
setup.py
geo_to_hca/__init__.py
geo_to_hca/config.py
geo_to_hca/geo_to_hca.py
geo_to_hca/pubmed_id_to_hca_publication.py
geo_to_hca.egg-info/PKG-INFO
geo_to_hca.egg-info/SOURCES.txt
geo_to_hca.egg-info/dependency_links.txt
geo_to_hca.egg-info/entry_points.txt
geo_to_hca.egg-info/requires.txt
geo_to_hca.egg-info/top_level.txt
geo_to_hca/utils/__init__.py
geo_to_hca/utils/entrez_client.py
geo_to_hca/utils/get_attribs.py
geo_to_hca/utils/get_tab.py
geo_to_hca/utils/handle_errors.py
geo_to_hca/utils/parse_reads.py
geo_to_hca/utils/sra_utils.py
geo_to_hca/utils/utils.py
template/__init__.py
template/hca_template.xlsx