Metadata-Version: 2.1
Name: geo-to-hca
Version: 1.0.21
Summary: A tool to assist in the automatic conversion of geo metadata to hca metadata standard
Home-page: https://github.com/ebi-ait/geo_to_hca
Author: Ami Day, Alegria Aclan, Enrique Sapena Ventura, Wei Kheng Teh, Amnon Khen
Author-email: ami@ebi.ac.uk, aaclan@ebi.ac.uk, enrique@ebi.ac.uk, wteh@ebi.ac.uk, amnon@ebi.ac.uk
Classifier: Programming Language :: Python :: 3.10
Classifier: License :: OSI Approved :: Apache Software License
